[
  {
    "MaLop": "L001",
    "TenLop": "10A1",
    "GiaoVienChuNhiem": {
      "MaGV": "GV001",
      "HoTen": "Nguyễn Văn A",
      "NgaySinh": "1980-05-15",
      "GioiTinh": "Nam",
      "DiaChi": "Hà Nội"
    }
  },
  {
    "MaLop": "L002",
    "TenLop": "10A2",
    "GiaoVienChuNhiem": {
      "MaGV": "GV002",
      "HoTen": "Trần Thị B",
      "NgaySinh": "1985-08-20",
      "GioiTinh": "Nữ",
      "DiaChi": "Hồ Chí Minh"
    }
  },
  {
    "MaLop": "L003",
    "TenLop": "11A1",
    "GiaoVienChuNhiem": {
      "MaGV": "GV003",
      "HoTen": "Lê Văn C",
      "NgaySinh": "1982-03-10",
      "GioiTinh": "Nam",
      "DiaChi": "Đà Nẵng"
    }
  },
  {
    "MaLop": "L004",
    "TenLop": "11A2",
    "GiaoVienChuNhiem": {
     "MaGV": "GV004",
    "HoTen": "Phạm Thị Dương",
    "NgaySinh": "1984-11-25",
    "GioiTinh": "Nữ",
    "DiaChi": "Huế"
    }
  },
 {
    "MaLop": "L005",
    "TenLop": "12A1",
    "GiaoVienChuNhiem": {
      "MaGV": "GV005",
    "HoTen": "Võ Minh Đạt",
    "NgaySinh": "1988-07-30",
    "GioiTinh": "Nam",
    "DiaChi": "Cần Thơ"
    }
  },
{
    "MaLop": "L006",
    "TenLop": "12A2",
    "GiaoVienChuNhiem": {
     "MaGV": "GV006",
    "HoTen": "Lý Văn Sáng",
    "NgaySinh": "1983-12-15",
    "GioiTinh": "Nam",
    "DiaChi": "TPHCM"

    }
  }
]